Metadata-Version: 2.1
Name: quick-sqlite
Version: 1.5
Summary: This library can you help you use sqlite3 much easier and faster.
Home-page: https://quick-sqlite.readthedocs.io/en/latest/index.html
Author: Spark Drago
Author-email: huzaifa.farooq05@gmail.com
License: MIT
Download-URL: https://github.com/SparkDrago05/quick_sqlite/
Keywords: sqlite,sqlite3,quick,quick_sqlite,sqlite3_helper,fast_sqlite
Platform: UNKNOWN
Classifier: Development Status :: 4 - Beta
Classifier: Intended Audience :: Developers
Classifier: Topic :: Software Development :: Build Tools
Classifier: License :: OSI Approved :: MIT License
Classifier: Programming Language :: Python :: 3
License-File: LICENSE
